fullscript_spellbook-2.1.6.dist-info/licenses/LICENSE
spellbook/.DS_Store
spellbook/__init__.py
spellbook/db_magic.py
spellbook/drive_magic.py
spellbook/sheet_magic.py
spellbook/stats_magic.py
spellbook/utils.py
spellbook/wizards/__init__.py
spellbook/wizards/wizard1.txt
spellbook/wizards/wizard10.txt
spellbook/wizards/wizard11.txt
spellbook/wizards/wizard12.txt
spellbook/wizards/wizard2.txt
spellbook/wizards/wizard3.txt
spellbook/wizards/wizard4.txt
spellbook/wizards/wizard5.txt
spellbook/wizards/wizard6.txt
spellbook/wizards/wizard7.txt
spellbook/wizards/wizard8.txt
spellbook/wizards/wizard9.txt
fullscript_spellbook-2.1.6.dist-info/METADATA
fullscript_spellbook-2.1.6.dist-info/WHEEL
fullscript_spellbook-2.1.6.dist-info/top_level.txt
fullscript_spellbook-2.1.6.dist-info/RECORD
